eapy/__init__.py
eapy/baseclasses.py
eapy/core.py
eapy/populations.py
eapy/selections.py
eapy/utils.py
eapy-0.2.2.dist-info/LICENSE
eapy-0.2.2.dist-info/METADATA
eapy-0.2.2.dist-info/WHEEL
eapy-0.2.2.dist-info/RECORD
